sound_lib/__init__.py
sound_lib/channel.py
sound_lib/config.py
sound_lib/encoder.py
sound_lib/input.py
sound_lib/listener.py
sound_lib/main.py
sound_lib/music.py
sound_lib/output.py
sound_lib/recording.py
sound_lib/stream.py
sound_lib/effects/__init__.py
sound_lib/effects/bass.py
sound_lib/effects/bass_fx.py
sound_lib/effects/effect.py
sound_lib/effects/tempo.py
sound_lib/external/__init__.py
sound_lib/external/paths.py
sound_lib/external/pybass.py
sound_lib/external/pybass_aac.py
sound_lib/external/pybass_alac.py
sound_lib/external/pybass_fx.py
sound_lib/external/pybassenc.py
sound_lib/external/pybassflac.py
sound_lib/external/pybassmidi.py
sound_lib/external/pybassmix.py
sound_lib/external/pybassopus.py
sound_lib/external/pybasswasapi.py
sound_lib/external/pybasswma.py
sound_lib/external/pytags.py
sound_lib/lib/x64/bass.dll
sound_lib/lib/x64/bass_aac.dll
sound_lib/lib/x64/bass_alac.dll
sound_lib/lib/x64/bass_fx.dll
sound_lib/lib/x64/bassalac.dll
sound_lib/lib/x64/bassflac.dll
sound_lib/lib/x64/bassmidi.dll
sound_lib/lib/x64/bassmix.dll
sound_lib/lib/x64/bassopus.dll
sound_lib/lib/x64/basswasapi.dll
sound_lib/lib/x64/basswma.dll
sound_lib/lib/x64/libbass.dylib
sound_lib/lib/x64/libbass.so
sound_lib/lib/x64/libbass_aac.so
sound_lib/lib/x64/libbass_alac.so
sound_lib/lib/x64/libbass_fx.dylib
sound_lib/lib/x64/libbass_fx.so
sound_lib/lib/x64/libbassalac.so
sound_lib/lib/x64/libbassenc.so
sound_lib/lib/x64/libbassflac.dylib
sound_lib/lib/x64/libbassflac.so
sound_lib/lib/x64/libbassmidi.dylib
sound_lib/lib/x64/libbassmidi.so
sound_lib/lib/x64/libbassmix.so
sound_lib/lib/x64/libbassopus.dylib
sound_lib/lib/x64/libbassopus.so
sound_lib/lib/x64/libtags.so
sound_lib/lib/x64/tags.dll
sound_lib/lib/x86/bass.dll
sound_lib/lib/x86/bass_aac.dll
sound_lib/lib/x86/bass_alac.dll
sound_lib/lib/x86/bass_fx.dll
sound_lib/lib/x86/bassalac.dll
sound_lib/lib/x86/bassenc.dll
sound_lib/lib/x86/bassflac.dll
sound_lib/lib/x86/bassmidi.dll
sound_lib/lib/x86/bassmix.dll
sound_lib-0.83.dist-info/LICENSE
sound_lib-0.83.dist-info/METADATA
sound_lib-0.83.dist-info/WHEEL
sound_lib-0.83.dist-info/top_level.txt
sound_lib-0.83.dist-info/RECORD
