Metadata-Version: 1.1
Name: sound_lib
Version: 0.83
Summary: Pythonic wrapper to the Bass sound library and various add-ons
Home-page: UNKNOWN
Author: Christopher Toth
Author-email: q@q-continuum.net
License: UNKNOWN
Platform: UNKNOWN
Classifier: Development Status :: 5 - Production/Stable   
Classifier: Intended Audience :: Developers
Classifier: Programming Language :: Python :: 2
Classifier: Programming Language :: Python :: 3
Classifier: License :: OSI Approved :: MIT License
Classifier: Topic :: Software Development :: Libraries
